LICENSE.txt
MANIFEST.in
README.md
requirements.txt
setup.cfg
setup.py
betterconfigclient/__init__.py
betterconfigclient/autopollingcachepolicy.py
betterconfigclient/betterconfigclient.py
betterconfigclient/configcache.py
betterconfigclient/configfetcher.py
betterconfigclient/interfaces.py
betterconfigclient/lazyloadingcachepolicy.py
betterconfigclient/manualpollingcachepolicy.py
betterconfigclient/readwritelock.py
betterconfigclient/version.py
betterconfigclient_python.egg-info/PKG-INFO
betterconfigclient_python.egg-info/SOURCES.txt
betterconfigclient_python.egg-info/dependency_links.txt
betterconfigclient_python.egg-info/requires.txt
betterconfigclient_python.egg-info/top_level.txt