Metadata-Version: 1.1
Name: betterconfigclient-python
Version: 1.0.4
Summary: BetterConfig library for Python. https://betterconfig.com
Home-page: https://github.com/BetterConfig/BetterConfigClient-python
Author: BetterConfig
Author-email: developer@betterconfig.com
License: MIT
Platform: UNKNOWN
Classifier: Intended Audience :: Developers
Classifier: License :: OSI Approved :: Apache Software License
Classifier: Operating System :: OS Independent
Classifier: Programming Language :: Python :: 2
Classifier: Programming Language :: Python :: 2.7
Classifier: Programming Language :: Python :: 3
Classifier: Programming Language :: Python :: 3.3
Classifier: Programming Language :: Python :: 3.4
Classifier: Programming Language :: Python :: 3.5
Classifier: Programming Language :: Python :: 3.6
Classifier: Topic :: Software Development
Classifier: Topic :: Software Development :: Libraries
